vimania_uri_rs-2.0.3.dist-info/METADATA
vimania_uri_rs-2.0.3.dist-info/WHEEL
vimania_uri_rs-2.0.3.dist-info/licenses/LICENSE
vimania_uri_rs.libs/libcrypto-fca80f7e.so.3
vimania_uri_rs.libs/libssl-e50e007b.so.3
vimania_uri_rs/__init__.py
vimania_uri_rs/vimania_uri_rs.cpython-313-x86_64-linux-gnu.so
vimania_uri_rs-2.0.3.dist-info/RECORD
