Metadata-Version: 2.4
Name: vimania_uri_rs
Version: 2.0.3
Classifier: Programming Language :: Rust
Classifier: Programming Language :: Python :: Implementation :: CPython
License-File: LICENSE
Summary: Advanced URI handling for Vim with Rust performance
Author-email: sysid <sysid@gmx.de>
License-Expression: BSD-3-Clause
Requires-Python: >=3.10
Project-URL: Source, https://github.com/sysid/vimania-uri-rs
